opsbot/__init__.py
opsbot/api_client.py
opsbot/chat_session.py
opsbot/cli.py
opsbot/config.py
opsbot/core.py
opsbot/file_handler.py
opsbot/prompts/default_code_prompt.txt
opsbot_prompt_generator-2.0.0.dist-info/METADATA
opsbot_prompt_generator-2.0.0.dist-info/WHEEL
opsbot_prompt_generator-2.0.0.dist-info/entry_points.txt
opsbot_prompt_generator-2.0.0.dist-info/top_level.txt
opsbot_prompt_generator-2.0.0.dist-info/RECORD
