Metadata-Version: 2.4
Name: opsbot-prompt-generator
Version: 2.0.0
Summary: 一个CLI工具，用于与项目交互并与AI模型通信。
Author-email: Your Name <you@example.com>
License: MIT License
Classifier: Programming Language :: Python :: 3
Classifier: Operating System :: OS Independent
Requires-Python: >=3.8
Requires-Dist: openai>=1.0.0
Requires-Dist: patch-ng>=1.17
Requires-Dist: click>=8.0
Requires-Dist: prompt-toolkit>=3.0
